backports/asyncio/runner/__init__.py
backports/asyncio/runner/patch.py
backports/asyncio/runner/py.typed
backports/asyncio/runner/runner.py
backports/asyncio/runner/runner.pyi
backports/asyncio/runner/tasks.py
backports_asyncio_runner-1.1.0.dist-info/METADATA
backports_asyncio_runner-1.1.0.dist-info/WHEEL
backports_asyncio_runner-1.1.0.dist-info/licenses/LICENSE.md
backports_asyncio_runner-1.1.0.dist-info/RECORD
