Metadata-Version: 2.3
Name: backports.asyncio.runner
Version: 1.1.0
Summary: Backport of asyncio.Runner, a context manager that controls event loop life cycle.
Project-URL: Homepage, https://github.com/samypr100/backports.asyncio.runner
Project-URL: Changelog, https://github.com/samypr100/backports.asyncio.runner/blob/main/CHANGELOG.md
Author-email: samypr100 <3933065+samypr100@users.noreply.github.com>
License: PSF-2.0
License-File: LICENSE.md
Keywords: asyncio,asyncio.Runner,backports,backports.asyncio,backports.asyncio.Runner
Classifier: Development Status :: 5 - Production/Stable
Classifier: Intended Audience :: Developers
Classifier: License :: OSI Approved :: Python Software Foundation License
Classifier: Operating System :: OS Independent
Classifier: Programming Language :: Python
Classifier: Programming Language :: Python :: 3 :: Only
Classifier: Programming Language :: Python :: 3.8
Classifier: Programming Language :: Python :: 3.9
Classifier: Programming Language :: Python :: 3.10
Classifier: Topic :: Software Development :: Libraries :: Python Modules
Classifier: Typing :: Typed
Requires-Python: <3.11,>=3.8
